AUTHORS.rst
CONTRIBUTING.rst
HISTORY.rst
LICENSE
MANIFEST.in
README.rst
setup.py
coffee_table/__init__.py
coffee_table/models.py
coffee_table/static/js/coffee_table.js
coffee_table/templates/coffee_table/base.html
coffee_table/templates/coffee_table/coffee_table.html
coffee_table/templates/coffee_table/extra_columns.html
coffee_table/templates/coffee_table/extra_headers.html
coffee_table/templates/coffee_table/field.html
coffee_table/templatetags/__init__.py
coffee_table/templatetags/coffee_table.py
coffee_table/testproject/manage.py
coffee_table/testproject/testapp/__init__.py
coffee_table/testproject/testapp/models.py
coffee_table/testproject/testapp/tests.py
coffee_table/testproject/testapp/views.py
coffee_table/testproject/testapp/templates/base.html
coffee_table/testproject/testapp/templates/coffee_table/extra_columns.html
coffee_table/testproject/testapp/templates/coffee_table/extra_headers.html
coffee_table/testproject/testapp/templates/testapp/basic.html
coffee_table/testproject/testapp/templates/testapp/check.html
coffee_table/testproject/testapp/templates/testapp/css.html
coffee_table/testproject/testapp/templates/testapp/full.html
coffee_table/testproject/testapp/templates/testapp/help.html
coffee_table/testproject/testapp/templates/testapp/paging.html
coffee_table/testproject/testapp/templates/testapp/pkcol.html
coffee_table/testproject/testproject/__init__.py
coffee_table/testproject/testproject/settings.py
coffee_table/testproject/testproject/urls.py
coffee_table/testproject/testproject/wsgi.py
django_coffee_table.egg-info/PKG-INFO
django_coffee_table.egg-info/SOURCES.txt
django_coffee_table.egg-info/dependency_links.txt
django_coffee_table.egg-info/not-zip-safe
django_coffee_table.egg-info/requires.txt
django_coffee_table.egg-info/top_level.txt